senseport/__init__.py
senseport/augments/__init__.py
senseport/models/Autoencode.py
senseport/models/Autoencoder.py
senseport/models/LSTM.py
senseport/models/__init__.py
senseport/models/alexnet.py
senseport/models/attention.py
senseport/models/cct.py
senseport/models/deeplab.py
senseport/models/deeplabv3p.py
senseport/models/densenet.py
senseport/models/googlenet.py
senseport/models/inceptionv3.py
senseport/models/inceptionv4.py
senseport/models/mobilenet.py
senseport/models/mobilenetv1.py
senseport/models/mobilenetv2.py
senseport/models/mobilenetv3.py
senseport/models/nasnet.py
senseport/models/preactresnet.py
senseport/models/resnet.py
senseport/models/resnext.py
senseport/models/rir.py
senseport/models/rnn.py
senseport/models/sealex.py
senseport/models/senet.py
senseport/models/shufflenet.py
senseport/models/shufflenetv2.py
senseport/models/simple_vit_1d.py
senseport/models/squeezenet.py
senseport/models/stochasticdepth.py
senseport/models/unet.py
senseport/models/vgg.py
senseport/models/vit.py
senseport/models/wideresidual.py
senseport/models/xception.py
senseport-0.0.2.dist-info/LICENSE
senseport-0.0.2.dist-info/METADATA
senseport-0.0.2.dist-info/WHEEL
senseport-0.0.2.dist-info/top_level.txt
senseport-0.0.2.dist-info/RECORD
